hpcflow/__init__.py
hpcflow/__pyinstaller/__init__.py
hpcflow/__pyinstaller/hook-hpcflow.py
hpcflow/_version.py
hpcflow/app.py
hpcflow/cli.py
hpcflow/data/demo_data_manifest/__init__.py
hpcflow/data/demo_data_manifest/demo_data_manifest.json
hpcflow/data/jinja_templates/__init__.py
hpcflow/data/jinja_templates/test/test_template.txt
hpcflow/data/programs/__init__.py
hpcflow/data/programs/hello_world/README.md
hpcflow/data/programs/hello_world/hello_world.c
hpcflow/data/programs/hello_world/linux/hello_world
hpcflow/data/programs/hello_world/macos/hello_world
hpcflow/data/programs/hello_world/win/hello_world.exe
hpcflow/data/scripts/__init__.py
hpcflow/data/scripts/bad_script.py
hpcflow/data/scripts/demo_task_1_generate_t1_infile_1.py
hpcflow/data/scripts/demo_task_1_generate_t1_infile_2.py
hpcflow/data/scripts/demo_task_1_parse_p3.py
hpcflow/data/scripts/do_nothing.py
hpcflow/data/scripts/env_specifier_test/input_file_generator_pass_env_spec.py
hpcflow/data/scripts/env_specifier_test/main_script_test_pass_env_spec.py
hpcflow/data/scripts/env_specifier_test/output_file_parser_pass_env_spec.py
hpcflow/data/scripts/env_specifier_test/v1/input_file_generator_basic.py
hpcflow/data/scripts/env_specifier_test/v1/main_script_test_direct_in_direct_out.py
hpcflow/data/scripts/env_specifier_test/v1/output_file_parser_basic.py
hpcflow/data/scripts/env_specifier_test/v2/main_script_test_direct_in_direct_out.py
hpcflow/data/scripts/generate_t1_file_01.py
hpcflow/data/scripts/import_future_script.py
hpcflow/data/scripts/input_file_generator_basic.py
hpcflow/data/scripts/input_file_generator_basic_FAIL.py
hpcflow/data/scripts/input_file_generator_test_stdout_stderr.py
hpcflow/data/scripts/main_script_test_direct_in.py
hpcflow/data/scripts/main_script_test_direct_in_direct_out.py
hpcflow/data/scripts/main_script_test_direct_in_direct_out_2.py
hpcflow/data/scripts/main_script_test_direct_in_direct_out_2_fail_allowed.py
hpcflow_new2-0.2.0a268.dist-info/LICENSE
hpcflow_new2-0.2.0a268.dist-info/METADATA
hpcflow_new2-0.2.0a268.dist-info/WHEEL
hpcflow_new2-0.2.0a268.dist-info/entry_points.txt
hpcflow_new2-0.2.0a268.dist-info/RECORD
